standards_explorer_mcp/__init__.py
standards_explorer_mcp/__main__.py
standards_explorer_mcp/main.py
standards_explorer_mcp-0.1.0.dist-info/METADATA
standards_explorer_mcp-0.1.0.dist-info/WHEEL
standards_explorer_mcp-0.1.0.dist-info/entry_points.txt
standards_explorer_mcp-0.1.0.dist-info/RECORD
