Metadata-Version: 2.4
Name: standards-explorer-mcp
Version: 0.1.0
Summary: A Model Context Protocol (MCP) implementation for exploring standards from the Bridge2AI Standards Explorer.
Requires-Python: >=3.11
Requires-Dist: fastmcp>=2.12.5
Requires-Dist: httpx>=0.27.0
Provides-Extra: dev
Requires-Dist: pytest-asyncio>=0.23.0; extra == 'dev'
Requires-Dist: pytest>=8.0.0; extra == 'dev'
